{
  "redirect_uri": "https://localhost:20230/callback",
  "scope": "publicData esi-skills.read_skills.v1 esi-search.search_structures.v1 esi-universe.read_structures.v1 esi-assets.read_assets.v1 esi-fittings.read_fittings.v1 esi-markets.structure_markets.v1 esi-corporations.read_structures.v1 esi-characters.read_agents_research.v1 esi-industry.read_character_jobs.v1 esi-markets.read_character_orders.v1 esi-characters.read_blueprints.v1 esi-industry.read_character_mining.v1 esi-corporations.read_facilities.v1 esi-characterstats.read.v1",
  "state": "eveHelper",
  "auth_store_path": "../resources/AuthTable.json",
  "authorize_url": "https://login.eveonline.com/v2/oauth/authorize/",
  "authorize_token_url": "https://login.eveonline.com/v2/oauth/token",
  "shutdown_server": "https://localhost:20230/shutdown"
}